multiSSH3.py
multissh3-6.6.dist-info/METADATA
multissh3-6.6.dist-info/WHEEL
multissh3-6.6.dist-info/entry_points.txt
multissh3-6.6.dist-info/top_level.txt
multissh3-6.6.dist-info/RECORD
